crdloadserver/__init__.py
crdloadserver/__main__.py
crdloadserver/cgi.py
crdloadserver-0.0.3.dist-info/LICENSE
crdloadserver-0.0.3.dist-info/METADATA
crdloadserver-0.0.3.dist-info/WHEEL
crdloadserver-0.0.3.dist-info/entry_points.txt
crdloadserver-0.0.3.dist-info/top_level.txt
crdloadserver-0.0.3.dist-info/RECORD
