Metadata-Version: 2.1
Name: crdloadserver
Version: 0.0.3
Summary: Python's http.server extended to include a file upload, delete and metadata for a directory.
Home-page: https://github.com/theycallmeloki/crdloadserver
Author: theycallmeloki
Author-email: ogmiladyloki@gmail.com
License: UNKNOWN
Platform: UNKNOWN
Classifier: Programming Language :: Python :: 3
Classifier: License :: OSI Approved :: MIT License
Classifier: Operating System :: OS Independent
Requires-Python: >=3.8
